[
    {
        "_": "Message",
        "id": 877,
        "peer_id": {
            "_": "PeerChannel",
            "channel_id": 1408065903
        },
        "date": "2022-10-31T14:42:17+00:00",
        "message": "Nossa hist\u00f3ria s\u00e3o os nossos valores! Obrigado a todos os trabalhistas que lutaram para derrotar o autoritarismo e o retrocesso nas urnas e nas ruas. #PDT",
        "out": false,
        "mentioned": false,
        "media_unread": false,
        "silent": false,
        "post": true,
        "from_scheduled": false,
        "legacy": false,
        "edit_hide": false,
        "pinned": false,
        "from_id": null,
        "fwd_from": null,
        "via_bot_id": null,
        "reply_to": null,
        "media": {
            "_": "MessageMediaPhoto",
            "photo": {
                "_": "Photo",
                "id": 5116576617282513517,
                "access_hash": -4157177734827142319,
                "file_reference": [
                    2,
                    83,
                    237,
                    97,
                    111,
                    0,
                    0,
                    3,
                    109,
                    100,
                    26,
                    240,
                    185,
                    174,
                    243,
                    216,
                    61,
                    36,
                    177,
                    113,
                    239,
                    44,
                    171,
                    83,
                    15,
                    214,
                    151,
                    150,
                    150
                ],
                "date": "2022-10-31T14:42:17+00:00",
                "sizes": [
                    {
                        "_": "PhotoStrippedSize",
                        "type": "i",
                        "bytes": [
                            1,
                            40,
                            40,
                            175,
                            29,
                            188,
                            146,
                            174,
                            80,
                            2,
                            51,
                            143,
                            188,
                            41,
                            77,
                            180,
                            209,
                            150,
                            45,
                            31,
                            9,
                            130,
                            217,
                            198,
                            49,
                            86,
                            44,
                            21,
                            252,
                            178,
                            86,
                            54,
                            97,
                            188,
                            30,
                            8,
                            237,
                            248,
                            212,
                            205,
                            49,
                            54,
                            238,
                            239,
                            19,
                            144,
                            217,
                            89,
                            9,
                            199,
                            211,
                            142,
                            125,
                            104,
                            72,
                            222,
                            83,
                            105,
                            216,
                            207,
                            19,
                            255,
                            0,
                            211,
                            56,
                            241,
                            233,
                            182,
                            156,
                            214,
                            87,
                            56,
                            13,
                            229,
                            240,
                            125,
                            8,
                            239,
                            80,
                            214,
                            201,
                            157,
                            182,
                            42,
                            136,
                            95,
                            32,
                            6,
                            60,
                            142,
                            159,
                            157,
                            82,
                            118,
                            38,
                            102,
                            68,
                            177,
                            60,
                            71,
                            14,
                            0,
                            62,
                            153,
                            6,
                            138,
                            179,
                            168,
                            171,
                            111,
                            87,
                            42,
                            192,
                            31,
                            80,
                            63,
                            165,
                            21,
                            209,
                            7,
                            116,
                            115,
                            181,
                            169,
                            53,
                            132,
                            194,
                            43,
                            99,
                            148,
                            98,
                            12,
                            152,
                            4,
                            99,
                            175,
                            30,
                            245,
                            35,
                            57,
                            16,
                            52,
                            102,
                            22,
                            17,
                            225,
                            183,
                            28,
                            130,
                            65,
                            235,
                            235,
                            80,
                            218,
                            41,
                            107,
                            109,
                            187,
                            91,
                            253,
                            102,
                            224,
                            70,
                            59,
                            126,
                            53,
                            60,
                            146,
                            22,
                            134,
                            67,
                            229,
                            182,
                            10,
                            177,
                            206,
                            7,
                            67,
                            92,
                            200,
                            218,
                            127,
                            19,
                            41,
                            102,
                            47,
                            177,
                            99,
                            247,
                            126,
                            103,
                            251,
                            191,
                            55,
                            95,
                            90,
                            188,
                            178,
                            72,
                            80,
                            98,
                            23,
                            228,
                            123,
                            116,
                            199,
                            215,
                            214,
                            178,
                            9,
                            21,
                            169,
                            27,
                            48,
                            34,
                            69,
                            142,
                            77,
                            206,
                            7,
                            166,
                            56,
                            199,
                            244,
                            6,
                            129,
                            203,
                            114,
                            29,
                            66,
                            83,
                            44,
                            40,
                            68,
                            108,
                            163,
                            113,
                            228,
                            227,
                            173,
                            20,
                            93,
                            201,
                            186,
                            208,
                            126,
                            237,
                            130,
                            19,
                            148,
                            39,
                            191,
                            92,
                            209,
                            91,
                            67,
                            99,
                            23,
                            184,
                            219,
                            91,
                            152,
                            225,
                            140,
                            7,
                            220,
                            88,
                            103,
                            28,
                            116,
                            169,
                            159,
                            80,
                            136,
                            198,
                            234,
                            21,
                            185,
                            92,
                            14,
                            62,
                            180,
                            81,
                            88,
                            38,
                            117,
                            202,
                            146,
                            108,
                            204,
                            53,
                            120,
                            93,
                            64,
                            36,
                            89,
                            9,
                            147,
                            56,
                            193,
                            29,
                            135,
                            24,
                            162,
                            138,
                            168,
                            171,
                            153,
                            204,
                            108,
                            247,
                            81,
                            73,
                            110,
                            97,
                            80,
                            64,
                            92,
                            108,
                            52,
                            81,
                            69,
                            111,
                            21,
                            161,
                            131,
                            63
                        ]
                    },
                    {
                        "_": "PhotoSize",
                        "type": "m",
                        "w": 320,
                        "h": 320,
                        "size": 33200
                    },
                    {
                        "_": "PhotoSize",
                        "type": "x",
                        "w": 800,
                        "h": 800,
                        "size": 147116
                    },
                    {
                        "_": "PhotoSizeProgressive",
                        "type": "y",
                        "w": 1080,
                        "h": 1080,
                        "sizes": [
                            19806,
                            54251,
                            89115,
                            150843,
                            212300
                        ]
                    }
                ],
                "dc_id": 1,
                "has_stickers": false,
                "video_sizes": []
            },
            "ttl_seconds": null
        },
        "reply_markup": null,
        "entities": [
            {
                "_": "MessageEntityHashtag",
                "offset": 150,
                "length": 4
            }
        ],
        "views": 417,
        "forwards": 0,
        "replies": null,
        "edit_date": null,
        "post_author": null,
        "grouped_id": null,
        "restriction_reason": [],
        "ttl_period": null
    }
]